odoo/addons/account_move_post_date_user/README.rst
odoo/addons/account_move_post_date_user/__init__.py
odoo/addons/account_move_post_date_user/__manifest__.py
odoo/addons/account_move_post_date_user/i18n/account_move_post_date_user.pot
odoo/addons/account_move_post_date_user/i18n/it.po
odoo/addons/account_move_post_date_user/models/__init__.py
odoo/addons/account_move_post_date_user/models/account_move.py
odoo/addons/account_move_post_date_user/readme/CONTRIBUTORS.rst
odoo/addons/account_move_post_date_user/readme/DESCRIPTION.rst
odoo/addons/account_move_post_date_user/static/description/icon.png
odoo/addons/account_move_post_date_user/static/description/index.html
odoo/addons/account_move_post_date_user/tests/__init__.py
odoo/addons/account_move_post_date_user/tests/test_account_move_post_date_user.py
odoo/addons/account_move_post_date_user/views/account_move.xml
odoo13_addon_account_move_post_date_user-13.0.1.0.1.dev3.dist-info/METADATA
odoo13_addon_account_move_post_date_user-13.0.1.0.1.dev3.dist-info/WHEEL
odoo13_addon_account_move_post_date_user-13.0.1.0.1.dev3.dist-info/top_level.txt
odoo13_addon_account_move_post_date_user-13.0.1.0.1.dev3.dist-info/RECORD
